sql_testing_tools/BaseAccess.py
sql_testing_tools/Helper.py
sql_testing_tools/TokenProcessing.py
sql_testing_tools/__init__.py
sql_testing_tools-0.2.11.dist-info/licenses/LICENSE
sql_testing_tools-0.2.11.dist-info/METADATA
sql_testing_tools-0.2.11.dist-info/WHEEL
sql_testing_tools-0.2.11.dist-info/top_level.txt
sql_testing_tools-0.2.11.dist-info/RECORD
