Metadata-Version: 2.4
Name: sql_testing_tools
Version: 0.2.11
License-File: LICENSE
Requires-Dist: sqlparse>=0.5.1
Requires-Dist: requests>=2.32.3
Dynamic: description
Dynamic: description-content-type
Dynamic: license-file
Dynamic: requires-dist
